promptflow_clu/__init__.py
promptflow_clu/tools/__init__.py
promptflow_clu/tools/conversational_language_understanding.py
promptflow_clu/tools/utils.py
promptflow_clu/yamls/conversational_language_understanding.yaml
tests/__init__.py
tests/test_conversational_language_understanding.py
promptflow_clu-0.0.2.dist-info/METADATA
promptflow_clu-0.0.2.dist-info/WHEEL
promptflow_clu-0.0.2.dist-info/entry_points.txt
promptflow_clu-0.0.2.dist-info/top_level.txt
promptflow_clu-0.0.2.dist-info/RECORD
